wasmer_compiler_llvm/__init__.py
wasmer_compiler_llvm-1.1.0.dist-info/METADATA
wasmer_compiler_llvm-1.1.0.dist-info/WHEEL
wasmer_compiler_llvm-1.1.0.dist-info/top_level.txt
wasmer_compiler_llvm-1.1.0.dist-info/RECORD
