Metadata-Version: 2.1
Name: wasmer-compiler-llvm
Version: 1.1.0
Summary: Python extension to run WebAssembly binaries
Home-page: UNKNOWN
Author: The Wasmer Engineering Team
Author-email: engineering@wasmer.io
License: MIT
Platform: any
Classifier: Programming Language :: Python
Classifier: License :: OSI Approved :: MIT License
Classifier: Operating System :: OS Independent
